django_nine/__init__.py
django_nine/context_processors.py
django_nine/models.py
django_nine/user.py
django_nine/versions.py
django_nine/tests/__init__.py
django_nine/tests/base.py
django_nine/tests/test_context_processors.py
django_nine/tests/test_versions.py
nine/__init__.py
nine/user.py
nine/versions.py
django_nine-0.2.7.dist-info/LICENSE_GPL2.0.txt
django_nine-0.2.7.dist-info/LICENSE_LGPL_2.1.txt
django_nine-0.2.7.dist-info/METADATA
django_nine-0.2.7.dist-info/WHEEL
django_nine-0.2.7.dist-info/top_level.txt
django_nine-0.2.7.dist-info/RECORD
