Metadata-Version: 2.1
Name: django-nine
Version: 0.2.7
Summary: Version checking library.
Home-page: https://github.com/barseghyanartur/django-nine/
Author: Artur Barseghyan
Author-email: artur.barseghyan@gmail.com
License: GPL-2.0-only OR LGPL-2.1-or-later
Project-URL: Bug Tracker, https://github.com/barseghyanartur/django-nine/issues
Project-URL: Documentation, https://django-nine.readthedocs.io/
Project-URL: Source Code, https://github.com/barseghyanartur/django-nine
Project-URL: Changelog, https://django-nine.readthedocs.io/en/latest/changelog.html
Keywords: django,compatibility
Classifier: Programming Language :: Python :: 3
Classifier: Programming Language :: Python :: 3.7
Classifier: Programming Language :: Python :: 3.8
Classifier: Programming Language :: Python :: 3.9
Classifier: Programming Language :: Python :: 3.10
Classifier: Environment :: Web Environment
Classifier: License :: OSI Approved :: GNU General Public License v2 (GPLv2)
Classifier: License :: OSI Approved :: GNU Lesser General Public License v2 or later (LGPLv2+)
Classifier: Framework :: Django
Classifier: Intended Audience :: Developers
Classifier: Operating System :: OS Independent
Classifier: Development Status :: 4 - Beta
License-File: LICENSE_GPL2.0.txt
License-File: LICENSE_LGPL_2.1.txt
